{"timestamp": "2025-05-17T23:17:24.848338", "domain": "abcdefghijklmnopqrstuvwxyz123456789.example.com", "entropy": 5.13, "length": 35}
{"timestamp": "2025-05-17T23:17:24.894331", "domain": "abcdefghijklmnopqrstuvwxyz123456789.example.com", "entropy": 5.13, "length": 35}
{"timestamp": "2025-05-17T23:17:53.037493", "domain": "abcdefghijklmnopqrstuvwxyz123456789.example.com", "entropy": 5.13, "length": 35}
{"timestamp": "2025-05-17T23:17:53.038876", "domain": "abcdefghijklmnopqrstuvwxyz123456789.example.com", "entropy": 5.13, "length": 35}
{"timestamp": "2025-05-17T23:17:53.039463", "domain": "abcdefghijklmnopqrstuvwxyz123456789.example.com", "entropy": 5.13, "length": 35}
{"timestamp": "2025-05-17T23:17:53.052850", "domain": "abcdefghijklmnopqrstuvwxyz123456789.example.com", "entropy": 5.13, "length": 35}
{"timestamp": "2025-05-17T23:17:53.083325", "domain": "abcdefghijklmnopqrstuvwxyz123456789.example.com", "entropy": 5.13, "length": 35}
{"timestamp": "2025-05-17T23:17:53.088395", "domain": "abcdefghijklmnopqrstuvwxyz123456789.example.com", "entropy": 5.13, "length": 35}
{"timestamp": "2025-05-17T23:18:58.084714", "domain": "abcdefghijklmnopqrstuvwxyz123456789.example.com", "entropy": 5.13, "length": 35}
{"timestamp": "2025-05-17T23:18:58.085790", "domain": "abcdefghijklmnopqrstuvwxyz123456789.example.com", "entropy": 5.13, "length": 35}
{"timestamp": "2025-05-17T23:18:58.100789", "domain": "abcdefghijklmnopqrstuvwxyz123456789.example.com", "entropy": 5.13, "length": 35}
{"timestamp": "2025-05-17T23:18:58.130028", "domain": "abcdefghijklmnopqrstuvwxyz123456789.example.com", "entropy": 5.13, "length": 35}
{"timestamp": "2025-05-17T23:18:58.152805", "domain": "abcdefghijklmnopqrstuvwxyz123456789.example.com", "entropy": 5.13, "length": 35}
{"timestamp": "2025-05-17T23:18:58.154129", "domain": "abcdefghijklmnopqrstuvwxyz123456789.example.com", "entropy": 5.13, "length": 35}
{"timestamp": "2025-05-17T23:18:58.164176", "domain": "abcdefghijklmnopqrstuvwxyz123456789.example.com", "entropy": 5.13, "length": 35}
{"timestamp": "2025-05-17T23:18:58.165329", "domain": "abcdefghijklmnopqrstuvwxyz123456789.example.com", "entropy": 5.13, "length": 35}
{"timestamp": "2025-05-17T23:19:32.414613", "domain": "abcdefghijklmnopqrstuvwxyz123456789.example.com", "entropy": 5.13, "length": 35}
{"timestamp": "2025-05-17T23:19:32.415487", "domain": "abcdefghijklmnopqrstuvwxyz123456789.example.com", "entropy": 5.13, "length": 35}
{"timestamp": "2025-05-17T23:19:32.434559", "domain": "abcdefghijklmnopqrstuvwxyz123456789.example.com", "entropy": 5.13, "length": 35}
{"timestamp": "2025-05-17T23:19:32.438349", "domain": "abcdefghijklmnopqrstuvwxyz123456789.example.com", "entropy": 5.13, "length": 35}
{"timestamp": "2025-05-17T23:19:33.572194", "domain": "abcdefghijklmnopqrstuvwxyz123456789.example.com", "entropy": 5.13, "length": 35}
{"timestamp": "2025-05-17T23:19:33.573030", "domain": "abcdefghijklmnopqrstuvwxyz123456789.example.com", "entropy": 5.13, "length": 35}
{"timestamp": "2025-05-17T23:19:33.588740", "domain": "abcdefghijklmnopqrstuvwxyz123456789.example.com", "entropy": 5.13, "length": 35}
{"timestamp": "2025-05-17T23:19:33.589944", "domain": "abcdefghijklmnopqrstuvwxyz123456789.example.com", "entropy": 5.13, "length": 35}
{"timestamp": "2025-05-17T23:19:40.679709", "domain": "abcdefghijklmnopqrstuvwxyz6789.example.com", "entropy": 4.91, "length": 30}
{"timestamp": "2025-05-17T23:19:40.680347", "domain": "abcdefghijklmnopqrstuvwxyz6789.example.com", "entropy": 4.91, "length": 30}
{"timestamp": "2025-05-17T23:19:40.680882", "domain": "abcdefghijklmnopqrstuvwxyz6789.example.com", "entropy": 4.91, "length": 30}
{"timestamp": "2025-05-17T23:19:40.727427", "domain": "abcdefghijklmnopqrstuvwxyz6789.example.com", "entropy": 4.91, "length": 30}
{"timestamp": "2025-05-17T23:19:40.728026", "domain": "abcdefghijklmnopqrstuvwxyz6789.example.com", "entropy": 4.91, "length": 30}
{"timestamp": "2025-05-17T23:19:40.730782", "domain": "abcdefghijklmnopqrstuvwxyz6789.example.com", "entropy": 4.91, "length": 30}
{"timestamp": "2025-05-17T23:19:52.423418", "domain": "abcdefghijklmnopqrstuvwxyz.example.com", "entropy": 4.7, "length": 26}
{"timestamp": "2025-05-17T23:19:52.424531", "domain": "abcdefghijklmnopqrstuvwxyz.example.com", "entropy": 4.7, "length": 26}
{"timestamp": "2025-05-17T23:19:52.425429", "domain": "abcdefghijklmnopqrstuvwxyz.example.com", "entropy": 4.7, "length": 26}
{"timestamp": "2025-05-17T23:19:52.470129", "domain": "abcdefghijklmnopqrstuvwxyz.example.com", "entropy": 4.7, "length": 26}
{"timestamp": "2025-05-17T23:19:52.471503", "domain": "abcdefghijklmnopqrstuvwxyz.example.com", "entropy": 4.7, "length": 26}
{"timestamp": "2025-05-17T23:19:52.471916", "domain": "abcdefghijklmnopqrstuvwxyz.example.com", "entropy": 4.7, "length": 26}
